moodle_inscribe/__init__.py
moodle_inscribe/__main__.py
moodle_inscribe-3.9.1.dist-info/LICENSE
moodle_inscribe-3.9.1.dist-info/METADATA
moodle_inscribe-3.9.1.dist-info/WHEEL
moodle_inscribe-3.9.1.dist-info/entry_points.txt
moodle_inscribe-3.9.1.dist-info/top_level.txt
moodle_inscribe-3.9.1.dist-info/RECORD
