Metadata-Version: 2.1
Name: moodle-inscribe
Version: 3.9.1
Summary: Inscribe students into moodle courses by their email. Works with Moodle 3.9.
Home-page: https://github.com/JohannesEbke/moodle_inscribe
Author: Johannes Ebke
Author-email: johannes.ebke@hm.edu
License: UNKNOWN
Keywords: moodle education
Platform: UNKNOWN
Classifier: Development Status :: 4 - Beta
Classifier: Environment :: Console
Classifier: Intended Audience :: Education
Classifier: License :: OSI Approved :: MIT License
Classifier: Natural Language :: English
Classifier: Programming Language :: Python :: 3
Classifier: Programming Language :: Python :: 3.9
Requires-Dist: requests
